__init__.py
cli/__init__.py
cli/__main__.py
cli/commands/__init__.py
cli/commands/add.py
cli/commands/apply.py
cli/commands/get.py
cli/commands/remove.py
cli/commands/update.py
cli/commands/version.py
remap_badblocks/__init__.py
remap_badblocks/cli/__init__.py
remap_badblocks/cli/__main__.py
remap_badblocks/cli/commands/__init__.py
remap_badblocks/cli/commands/add.py
remap_badblocks/cli/commands/apply.py
remap_badblocks/cli/commands/get.py
remap_badblocks/cli/commands/remove.py
remap_badblocks/cli/commands/update.py
remap_badblocks/cli/commands/version.py
remap_badblocks/src/devices_config_constants.py
remap_badblocks/src/mapping.py
remap_badblocks/src/test_utils.py
remap_badblocks/src/badblocks/_compute_good_ranges.py
remap_badblocks/src/badblocks/_find_badblocks.py
remap_badblocks/src/badblocks/_mapping_generation.py
remap_badblocks/src/badblocks/_remap_badblocks.py
remap_badblocks/src/badblocks/badblocks.py
remap_badblocks/src/devices/__init__.py
remap_badblocks/src/devices/device_config.py
remap_badblocks/src/devices/devices_config.py
remap_badblocks/src/devices/exceptions.py
remap_badblocks/src/remappers/_check_applied_devices.py
remap_badblocks/src/remappers/_generate_dm_table.py
remap_badblocks/src/utils/__init__.py
remap_badblocks/src/utils/_get_device_info.py
remap_badblocks/src/utils/_iterable_bytes_converter.py
remap_badblocks/src/utils/_parse_inputs.py
remap_badblocks/src/utils/_run_command.py
remap_badblocks/src/utils/_sort_devices.py
remap_badblocks-0.7.dist-info/licenses/LICENSE
src/devices_config_constants.py
src/mapping.py
src/test_utils.py
src/badblocks/_compute_good_ranges.py
src/badblocks/_find_badblocks.py
src/badblocks/_mapping_generation.py
src/badblocks/_remap_badblocks.py
src/badblocks/badblocks.py
src/devices/__init__.py
src/devices/device_config.py
src/devices/devices_config.py
src/devices/exceptions.py
src/remappers/_check_applied_devices.py
src/remappers/_generate_dm_table.py
src/utils/__init__.py
src/utils/_get_device_info.py
src/utils/_iterable_bytes_converter.py
remap_badblocks-0.7.dist-info/METADATA
remap_badblocks-0.7.dist-info/WHEEL
remap_badblocks-0.7.dist-info/entry_points.txt
remap_badblocks-0.7.dist-info/top_level.txt
remap_badblocks-0.7.dist-info/RECORD
