Metadata-Version: 2.4
Name: remap_badblocks
Version: 0.7
Summary: CLI tool for remapping bad sectors on Linux disks using device-mapper
Author-email: Luigi Privitera <priviteraluigi98@gmail.com>
License-Expression: GPL-3.0-only
Project-URL: Repository, https://gitlab.com/Luigi-98/remap_badblocks.git
Project-URL: Issues, https://gitlab.com/Luigi-98/remap_badblocks/-/issues
Requires-Python: >=3.10
License-File: LICENSE
Provides-Extra: dev
Requires-Dist: mypy; extra == "dev"
Requires-Dist: flake8; extra == "dev"
Requires-Dist: ruff; extra == "dev"
Requires-Dist: pytest>=7.0; extra == "dev"
Requires-Dist: pre-commit; extra == "dev"
Requires-Dist: black; extra == "dev"
Requires-Dist: isort; extra == "dev"
Dynamic: license-file
